biobb_common/__init__.py
biobb_common/py.typed
biobb_common/command_wrapper/__init__.py
biobb_common/command_wrapper/cmd_wrapper.py
biobb_common/configuration/__init__.py
biobb_common/configuration/settings.py
biobb_common/generic/__init__.py
biobb_common/generic/biobb_object.py
biobb_common/generic/folder_test.py
biobb_common/test/__init__.py
biobb_common/tools/__init__.py
biobb_common/tools/file_utils.py
biobb_common/tools/test_fixtures.py
biobb_common-5.2.0.dist-info/licenses/LICENSE
biobb_common-5.2.0.dist-info/METADATA
biobb_common-5.2.0.dist-info/WHEEL
biobb_common-5.2.0.dist-info/entry_points.txt
biobb_common-5.2.0.dist-info/top_level.txt
biobb_common-5.2.0.dist-info/RECORD
