Metadata-Version: 2.4
Name: biobb_common
Version: 5.2.0
Summary: Biobb_common is the base package required to use the biobb packages.
Home-page: https://github.com/bioexcel/biobb_common
Author: Biobb developers
Author-email: pau.andrio@bsc.es
Project-URL: Documentation, http://biobb-common.readthedocs.io/en/latest/
Project-URL: Bioexcel, https://bioexcel.eu/
Keywords: Bioinformatics Workflows BioExcel Compatibility
Classifier: Development Status :: 5 - Production/Stable
Classifier: Programming Language :: Python :: 3.10
Classifier: Programming Language :: Python :: 3.11
Classifier: Programming Language :: Python :: 3.12
Classifier: License :: OSI Approved :: Apache Software License
Classifier: Operating System :: MacOS :: MacOS X
Classifier: Operating System :: POSIX
Classifier: Operating System :: Unix
Requires-Python: >=3.10
License-File: LICENSE
Requires-Dist: pyyaml
Requires-Dist: requests
Requires-Dist: biopython
Requires-Dist: jsonschema
Dynamic: author
Dynamic: author-email
Dynamic: classifier
Dynamic: description
Dynamic: description-content-type
Dynamic: home-page
Dynamic: keywords
Dynamic: license-file
Dynamic: project-url
Dynamic: requires-dist
Dynamic: requires-python
Dynamic: summary
